offlineimap_notify.py
offlineimap_notify-0.6.0.dist-info/LICENSE
offlineimap_notify-0.6.0.dist-info/METADATA
offlineimap_notify-0.6.0.dist-info/WHEEL
offlineimap_notify-0.6.0.dist-info/entry_points.txt
offlineimap_notify-0.6.0.dist-info/top_level.txt
offlineimap_notify-0.6.0.dist-info/RECORD
