Metadata-Version: 2.1
Name: offlineimap-notify
Version: 0.6.0
Summary: Wrapper for add notification sending to OfflineIMAP
Home-page: https://framagit.org/distopico/offlineimap-notify
Author: Raymond Wagenmaker and Distopico
Author-email: distopico@riseup.net
License: UNKNOWN
Download-URL: https://framagit.org/distopico/offlineimap-notify/-/archive/v0.6.0/offlineimap-notify-v0.6.0.tar.gz
Platform: UNKNOWN
Classifier: Programming Language :: Python :: 2.7
Classifier: License :: OSI Approved :: GNU Lesser General Public License v3 or later (LGPLv3+)
Requires-Python: >=2.7
Requires-Dist: offlineimap
